revenuecat_client/__init__.py
revenuecat_client/api/__init__.py
revenuecat_client/api/app/__init__.py
revenuecat_client/api/app/create_app.py
revenuecat_client/api/app/delete_app.py
revenuecat_client/api/app/get_app.py
revenuecat_client/api/app/list_apps.py
revenuecat_client/api/app/update_app.py
revenuecat_client/api/charts_metrics/__init__.py
revenuecat_client/api/charts_metrics/get_overview_metrics.py
revenuecat_client/api/customer/__init__.py
revenuecat_client/api/customer/create_customer.py
revenuecat_client/api/customer/delete_customer.py
revenuecat_client/api/customer/get_customer.py
revenuecat_client/api/customer/list_customer_active_entitlements.py
revenuecat_client/api/customer/list_customer_aliases.py
revenuecat_client/api/customer/list_customer_attributes.py
revenuecat_client/api/customer/list_customers.py
revenuecat_client/api/customer/list_purchases.py
revenuecat_client/api/customer/list_subscriptions.py
revenuecat_client/api/customer/set_customer_attributes.py
revenuecat_client/api/entitlement/__init__.py
revenuecat_client/api/entitlement/attach_products_to_entitlement.py
revenuecat_client/api/entitlement/create_entitlement.py
revenuecat_client/api/entitlement/delete_entitlement.py
revenuecat_client/api/entitlement/detach_products_from_entitlement.py
revenuecat_client/api/entitlement/get_entitlement.py
revenuecat_client/api/entitlement/get_products_from_entitlement.py
revenuecat_client/api/entitlement/list_entitlements.py
revenuecat_client/api/entitlement/update_entitlement.py
revenuecat_client/api/invoice/__init__.py
revenuecat_client/api/invoice/get_invoice.py
revenuecat_client/api/invoice/list_customer_invoices.py
revenuecat_client/api/offering/__init__.py
revenuecat_client/api/offering/create_offering.py
revenuecat_client/api/offering/delete_offering.py
revenuecat_client/api/offering/get_offering.py
revenuecat_client/api/offering/list_offerings.py
revenuecat_client/api/offering/update_offering.py
revenuecat_client/api/package/__init__.py
revenuecat_client-2.0.0.dist-info/AUTHORS.rst
revenuecat_client-2.0.0.dist-info/LICENSE
revenuecat_client-2.0.0.dist-info/METADATA
revenuecat_client-2.0.0.dist-info/WHEEL
revenuecat_client-2.0.0.dist-info/RECORD
