Metadata-Version: 2.3
Name: revenuecat-client
Version: 2.0.0
Summary: A client library for accessing RevenueCat API v2
Author: Yurii Havrylko
Requires-Python: >=3.8,<4.0
Classifier: Programming Language :: Python :: 3
Classifier: Programming Language :: Python :: 3.8
Classifier: Programming Language :: Python :: 3.9
Classifier: Programming Language :: Python :: 3.10
Classifier: Programming Language :: Python :: 3.11
Classifier: Programming Language :: Python :: 3.12
Classifier: Programming Language :: Python :: 3.13
Requires-Dist: attrs (>=21.3.0)
Requires-Dist: httpx (>=0.20.0,<0.27.0)
Requires-Dist: python-dateutil (>=2.8.0,<3.0.0)
